alibabacloud_iqs20241121/__init__.py
alibabacloud_iqs20241121/client.py
alibabacloud_iqs20241121/models/__init__.py
alibabacloud_iqs20241121/models/_account_create_cmd.py
alibabacloud_iqs20241121/models/_account_credential_dto.py
alibabacloud_iqs20241121/models/_account_info_manage_request.py
alibabacloud_iqs20241121/models/_apply_formal_service_cmd.py
alibabacloud_iqs20241121/models/_apply_formal_service_request.py
alibabacloud_iqs20241121/models/_apply_formal_service_response.py
alibabacloud_iqs20241121/models/_apply_formal_service_response_body.py
alibabacloud_iqs20241121/models/_base_response.py
alibabacloud_iqs20241121/models/_bill_down_or_upgrade_cmd.py
alibabacloud_iqs20241121/models/_check_account_type_response.py
alibabacloud_iqs20241121/models/_check_account_type_response_body.py
alibabacloud_iqs20241121/models/_download_api_call_daily_detail_cmd.py
alibabacloud_iqs20241121/models/_download_api_call_daily_detail_request.py
alibabacloud_iqs20241121/models/_download_api_call_daily_detail_response.py
alibabacloud_iqs20241121/models/_download_api_call_daily_detail_response_body.py
alibabacloud_iqs20241121/models/_download_metering_daily_detail_cmd.py
alibabacloud_iqs20241121/models/_download_metering_daily_detail_request.py
alibabacloud_iqs20241121/models/_download_metering_daily_detail_response.py
alibabacloud_iqs20241121/models/_download_metering_daily_detail_response_body.py
alibabacloud_iqs20241121/models/_expand_search_expired_time_request.py
alibabacloud_iqs20241121/models/_expand_search_expired_time_response.py
alibabacloud_iqs20241121/models/_expend_expired_time_request.py
alibabacloud_iqs20241121/models/_get_account_config_info_response.py
alibabacloud_iqs20241121/models/_get_account_config_info_response_body.py
alibabacloud_iqs20241121/models/_get_account_review_record_response.py
alibabacloud_iqs20241121/models/_get_account_review_record_response_body.py
alibabacloud_iqs20241121/models/_get_metering_summary_request.py
alibabacloud_iqs20241121-1.0.0.dist-info/LICENSE
alibabacloud_iqs20241121-1.0.0.dist-info/METADATA
alibabacloud_iqs20241121-1.0.0.dist-info/WHEEL
alibabacloud_iqs20241121-1.0.0.dist-info/top_level.txt
alibabacloud_iqs20241121-1.0.0.dist-info/RECORD
